my_method/__init__.py
my_method/__version__.py
my_method/common.py
my_method/directory_create/__init__.py
my_method/directory_create/directory_create.py
my_method/directory_listing/__init__.py
my_method/directory_listing/directory_listing.py
my_method/my_input/__init__.py
my_method/my_input/my_input.py
my_method/version_check/__init__.py
my_method/version_check/version_check.py
ymorishima030_method-2.1.0.dist-info/LICENCE
ymorishima030_method-2.1.0.dist-info/METADATA
ymorishima030_method-2.1.0.dist-info/WHEEL
ymorishima030_method-2.1.0.dist-info/top_level.txt
ymorishima030_method-2.1.0.dist-info/RECORD
